spotify/__init__.py
spotify/client.py
spotify/errors.py
spotify/http.py
spotify/models/__init__.py
spotify/models/album.py
spotify/models/artist.py
spotify/models/base.py
spotify/models/common.py
spotify/models/library.py
spotify/models/player.py
spotify/models/playlist.py
spotify/models/track.py
spotify/models/typing.py
spotify/models/user.py
spotify/oauth.py
spotify/sync/__init__.py
spotify/sync/models.py
spotify/sync/thread.py
spotify/utils.py
spotify-0.10.1.dist-info/LICENSE
spotify-0.10.1.dist-info/WHEEL
spotify-0.10.1.dist-info/METADATA
spotify-0.10.1.dist-info/RECORD
