Metadata-Version: 2.1
Name: spotify
Version: 0.10.1
Summary: spotify.py is an asynchronous API wrapper for Spotify written in Python.
Home-page: https://github.com/mental32/spotify.py
License: MIT
Keywords: spotify,python,async,library,api
Author: mental
Author-email: m3nta1@yahoo.com
Requires-Python: >=3.6,<4.0
Classifier: Intended Audience :: Developers
Classifier: License :: OSI Approved :: MIT License
Classifier: Natural Language :: English
Classifier: Operating System :: OS Independent
Classifier: Programming Language :: Python :: 3
Classifier: Programming Language :: Python :: 3.6
Classifier: Programming Language :: Python :: 3.7
Classifier: Programming Language :: Python :: 3.8
Classifier: Topic :: Internet
Classifier: Topic :: Software Development :: Libraries
Classifier: Topic :: Software Development :: Libraries :: Python Modules
Classifier: Topic :: Utilities
Requires-Dist: aiohttp (>=3.6,<4.0)
Requires-Dist: backoff (>=1.10.0,<2.0.0)
Project-URL: Documentation, https://spotifypy.readthedocs.io/en/latest/
Project-URL: Repository, https://github.com/mental32/spotify.py
